Makefile
__init__.py
main.py
setup.py
hailstone_calculator/__init__.py
hailstone_calculator/calculator.py
hailstone_calculator.egg-info/PKG-INFO
hailstone_calculator.egg-info/SOURCES.txt
hailstone_calculator.egg-info/dependency_links.txt
hailstone_calculator.egg-info/top_level.txt