Metadata-Version: 2.1
Name: hailstone_calculator
Version: 0.0.16
Summary: Hailstone calculator
Author: Ibrahim Animashaun
License: MIT
